keycloak_oidc/__init__.py
keycloak_oidc/auth.py
keycloak_oidc/default_settings.py
keycloak_oidc/urls.py
keycloak_oidc/utils.py
keycloak_oidc/views.py
keycloak_oidc/drf/__init__.py
keycloak_oidc/drf/permissions.py
tests/__init__.py
tests/settings.py
tests/test_auth.py
tests/test_permissions.py
tests/test_utils.py
tests/test_views.py
tests/urls.py
datapunt_keycloak_oidc-0.5.1.dist-info/LICENSE
datapunt_keycloak_oidc-0.5.1.dist-info/METADATA
datapunt_keycloak_oidc-0.5.1.dist-info/WHEEL
datapunt_keycloak_oidc-0.5.1.dist-info/top_level.txt
datapunt_keycloak_oidc-0.5.1.dist-info/RECORD
