Metadata-Version: 2.1
Name: datapunt-keycloak-oidc
Version: 0.5.1
Summary: A simple Django app to use keycloak over OIDC
Home-page: https://github.com/Amsterdam/keycloak_oidc
Author: Datapunt Amsterdam
Author-email: datapunt@amsterdam.nl
License: Mozilla Public License 2.0
Platform: UNKNOWN
Classifier: Environment :: Web Environment
Classifier: Framework :: Django
Classifier: Framework :: Django :: 2.2
Classifier: Intended Audience :: Developers
Classifier: License :: OSI Approved :: Mozilla Public License 2.0 (MPL 2.0)
Classifier: Operating System :: OS Independent
Classifier: Programming Language :: Python
Classifier: Programming Language :: Python :: 3.5
Classifier: Programming Language :: Python :: 3.6
Classifier: Topic :: Internet :: WWW/HTTP
Classifier: Topic :: Internet :: WWW/HTTP :: Dynamic Content
Requires-Dist: mozilla-django-oidc (~=1.2)
Provides-Extra: dev
Requires-Dist: pytest ; extra == 'dev'
Requires-Dist: pytest-cov ; extra == 'dev'
Requires-Dist: twine ; extra == 'dev'
